augur_solidity_flattener-0.2.5.data/scripts/solidity_flattener
augur_solidity_flattener-0.2.5.dist-info/DESCRIPTION.rst
augur_solidity_flattener-0.2.5.dist-info/METADATA
augur_solidity_flattener-0.2.5.dist-info/RECORD
augur_solidity_flattener-0.2.5.dist-info/WHEEL
augur_solidity_flattener-0.2.5.dist-info/metadata.json
augur_solidity_flattener-0.2.5.dist-info/top_level.txt
flattener/__init__.py
flattener/core.py
