Metadata-Version: 2.0
Name: augur-solidity-flattener
Version: 0.2.5
Summary: Flattens Solidity code that uses imports into a single file.
Home-page: https://github.com/AugurProject/solidity-flattener
Author: Eric Huang, BlockCAT Technologies Inc.
Author-email: team@blockcat.io
License: UNKNOWN
Platform: UNKNOWN
